LICENSE
MANIFEST.in
README.rst
setup.py
gears_stylus/__init__.py
gears_stylus/compiler.js
gears_stylus/compiler.py
gears_stylus.egg-info/PKG-INFO
gears_stylus.egg-info/SOURCES.txt
gears_stylus.egg-info/dependency_links.txt
gears_stylus.egg-info/top_level.txt
gears_stylus/node_modules/nib/.npmignore
gears_stylus/node_modules/nib/.travis.yml
gears_stylus/node_modules/nib/LICENSE
gears_stylus/node_modules/nib/Readme.md
gears_stylus/node_modules/nib/index.styl
gears_stylus/node_modules/nib/package.json
gears_stylus/node_modules/nib/iconic/demo.html
gears_stylus/node_modules/nib/iconic/iconic.css
gears_stylus/node_modules/nib/iconic/iconic_stroke.eot
gears_stylus/node_modules/nib/iconic/iconic_stroke.otf
gears_stylus/node_modules/nib/iconic/iconic_stroke.svg
gears_stylus/node_modules/nib/iconic/iconic_stroke.ttf
gears_stylus/node_modules/nib/lib/nib.js
gears_stylus/node_modules/nib/lib/nib/border.styl
gears_stylus/node_modules/nib/lib/nib/clearfix.styl
gears_stylus/node_modules/nib/lib/nib/color-image.styl
gears_stylus/node_modules/nib/lib/nib/config.styl
gears_stylus/node_modules/nib/lib/nib/flex.styl
gears_stylus/node_modules/nib/lib/nib/gradients.styl
gears_stylus/node_modules/nib/lib/nib/iconic.styl
gears_stylus/node_modules/nib/lib/nib/image.styl
gears_stylus/node_modules/nib/lib/nib/index.styl
gears_stylus/node_modules/nib/lib/nib/overflow.styl
gears_stylus/node_modules/nib/lib/nib/positions.styl
gears_stylus/node_modules/nib/lib/nib/reset.styl
gears_stylus/node_modules/nib/lib/nib/size.styl
gears_stylus/node_modules/nib/lib/nib/vendor.styl
gears_stylus/node_modules/nib/lib/nib/text/aliases.styl
gears_stylus/node_modules/nib/lib/nib/text/ellipsis.styl
gears_stylus/node_modules/nib/lib/nib/text/hide-text.styl
gears_stylus/node_modules/nib/lib/nib/text/index.styl
gears_stylus/node_modules/nib/lib/nib/text/replace-text.styl
gears_stylus/node_modules/nib/lib/nodes/color-image.js
gears_stylus/node_modules/nib/lib/nodes/gradient.js
gears_stylus/node_modules/nib/lib/nodes/vendor-helpers.js
gears_stylus/node_modules/nib/node_modules/.bin/stylus
gears_stylus/node_modules/nib/node_modules/stylus/LICENSE
